jhtalib/__init__.py
jhtalib/decorators.py
jhtalib/example.py
jhtalib/helpers.py
jhtalib/behavioral_techniques/__init__.py
jhtalib/behavioral_techniques/behavioral_techniques.py
jhtalib/candlestick/__init__.py
jhtalib/candlestick/candlestick.py
jhtalib/cycle_indicators/__init__.py
jhtalib/cycle_indicators/cycle_indicators.py
jhtalib/data/__init__.py
jhtalib/data/data.py
jhtalib/event_driven/__init__.py
jhtalib/event_driven/event_driven.py
jhtalib/experimental/__init__.py
jhtalib/experimental/experimental.py
jhtalib/general/__init__.py
jhtalib/general/general.py
jhtalib/information/__init__.py
jhtalib/information/information.py
jhtalib/math_functions/__init__.py
jhtalib/math_functions/math_functions.py
jhtalib/momentum_indicators/__init__.py
jhtalib/momentum_indicators/momentum_indicators.py
jhtalib/overlap_studies/__init__.py
jhtalib/overlap_studies/overlap_studies.py
jhtalib/pattern_recognition/__init__.py
jhtalib/pattern_recognition/pattern_recognition.py
jhtalib/price_transform/__init__.py
jhtalib/price_transform/price_transform.py
jhtalib/statistic_functions/__init__.py
jhtalib/statistic_functions/statistic_functions.py
jhtalib/uncategorised/__init__.py
jhtalib/uncategorised/uncategorised.py
jhtalib/volatility_indicators/__init__.py
jhtalib/volatility_indicators/volatility_indicators.py
jhtalib/volume_indicators/__init__.py
jhtalib/volume_indicators/volume_indicators.py
jhTAlib-20201228.0.dist-info/LICENSE
jhTAlib-20201228.0.dist-info/METADATA
jhTAlib-20201228.0.dist-info/WHEEL
jhTAlib-20201228.0.dist-info/top_level.txt
jhTAlib-20201228.0.dist-info/RECORD
