Metadata-Version: 2.1
Name: jhTAlib
Version: 20201228.0
Summary: Technical Analysis Library Time-Series
Home-page: https://github.com/joosthoeks/jhTAlib
Author: Joost Hoeks
Author-email: joosthoeks@gmail.com
License: UNKNOWN
Project-URL: Documentation, https://github.com/joosthoeks/jhTAlib/blob/master/README.md
Project-URL: Funding, https://github.com/joosthoeks/jhTAlib/stargazers
Project-URL: Say Thanks!, https://github.com/joosthoeks/jhTAlib/stargazers
Project-URL: Source, https://github.com/joosthoeks/jhTAlib
Project-URL: Tracker, https://github.com/joosthoeks/jhTAlib/issues
Platform: UNKNOWN
Classifier: License :: OSI Approved :: GNU General Public License v3 (GPLv3)
Classifier: Operating System :: OS Independent
Classifier: Programming Language :: Python :: 3
Requires-Python: >=3
